GENDIS-1.0.9.dist-info/METADATA
GENDIS-1.0.9.dist-info/RECORD
GENDIS-1.0.9.dist-info/WHEEL
GENDIS-1.0.9.dist-info/top_level.txt
gendis/__init__.py
gendis/genetic.py
gendis/mstamp_stomp.py
gendis/util.py
